entities/__init__.py
entities/execution.py
entities/mlmodel.py
entities/plot.py
entities/request.py
wizata-0.0.2.dist-info/LICENSE.txt
wizata-0.0.2.dist-info/METADATA
wizata-0.0.2.dist-info/WHEEL
wizata-0.0.2.dist-info/top_level.txt
wizata-0.0.2.dist-info/RECORD
