Metadata-Version: 2.1
Name: wizata
Version: 0.0.2
Summary: Wizata Data Science Toolkit
Author: Wizata S.A.
Author-email: info@wizata.com
License-File: LICENSE.txt
